{
    "data": {
        "result0":[
            {
                "img": "https://image.watsons.com.cn//upload/99725d3a.jpg?x-oss-process=image/quality,q_80/format,webp",
                "title": "LABO LABO毛孔细致化妆水2件套",
                "type":"必抢",
                "newprice":"￥228",
                "oldprice":"￥368"
            },{
                "img": "https://image.watsons.com.cn//upload/d2844be8.jpg?x-oss-process=image/quality,q_80/format,webp",
                "title": "LG竹盐喜马拉雅粉盐牙膏(清幽花香)30克",
                "type":"必抢",
                "newprice":"￥1",
                "oldprice":"￥12"
            },{
                "img": "https://image.watsons.com.cn//upload/2ffa3d25.jpg?x-oss-process=image/quality,q_80/format,webp",
                "title": "安热沙水能户外防晒乳SPF50+ PA++60ml",
                "type":"必抢",
                "newprice":"￥225",
                "oldprice":"￥298"
            },{
                "img": "https://image.watsons.com.cn//upload/efad2432.jpg?x-oss-process=image/quality,q_80/format,webp",
                "title": "屈臣氏燕窝沁白臻颜面膜 6片装",
                "type":"必抢",
                "newprice":"￥20.9",
                "oldprice":"￥79"
            },{
                "img": "https://image.watsons.com.cn//upload/60b16516.jpg?x-oss-process=image/quality,q_80/format,webp",
                "title": "Lumi胶原蛋白液态饮 50ml*3",
                "type":"必抢",
                "newprice":"￥46",
                "oldprice":"￥78"
            },{
                "img": "https://image.watsons.com.cn//upload/134645cb.jpg?x-oss-process=image/quality,q_80/format,webp",
                "title": "肌司研水滋养水盈补水面膜(黑臻版)35ml*10片",
                "type":"必抢",
                "newprice":"￥69",
                "oldprice":"￥99"
            },{
                "img": "https://image.watsons.com.cn//upload/1d55d607.jpg?x-oss-process=image/quality,q_80/format,webp",
                "title": "优理氏烟酰胺亮肤安瓶原液1ml*7支",
                "type":"必抢",
                "newprice":"￥99",
                "oldprice":"￥118"
            },{
                "img": "https://image.watsons.com.cn//upload/d724202c.jpg?x-oss-process=image/quality,q_80/format,webp",
                "title": "碧柔轻透倍护防晒乳SPF50+PA+++ 40ml",
                "type":"必抢",
                "newprice":"￥42",
                "oldprice":"￥59"
            }
        ],
        "result1":[
            {
                "img": "../img/index/1d55d607.jpg",
                "title": "优理氏烟酰胺亮肤安瓶原液1ml*7支",
                "type":"买1盒送4盒",
                "newprice":"￥99",
                "oldprice":"￥118"
            },{
                "img": "../img/index/efad2432.jpg",
                "title": "屈臣氏燕窝沁白臻颜面膜 6片装",
                "type":"满600送小米手环",
                "newprice":"￥20",
                "oldprice":"￥78"
            },{
                "img": "../img/index/62c3ed4f.jpg",
                "title": "S.A卓沿白金舒润保湿柔肤啫喱150ml",
                "type":"满600送小米手环",
                "newprice":"￥69",
                "oldprice":"￥139"
            },{
                "img": "../img/index/60b16516.jpg",
                "title": "Lumi胶原蛋白液态饮 50ml*3",
                "type":"满600送小米手环",
                "newprice":"￥46",
                "oldprice":"￥78"
            },{
                "img": "../img/index/fa42b3df.jpg",
                "title": "美迪惠尔水润保湿面膜(升级版) 27ml*10片",
                "type":"满600送小米手环",
                "newprice":"￥69",
                "oldprice":"￥108"
            },{
                "img": "../img/index/134645cb.jpg",
                "title": "肌司研水滋养水盈补水面膜(黑臻版)35ml*10片",
                "type":"满600送小米手环",
                "newprice":"￥69",
                "oldprice":"￥99"
            },{
                "img": "../img/index/2ffa3d25.jpg",
                "title": "安热沙水能户外防晒乳SPF50+ PA++++60ml",
                "type":"满600送小米手环",
                "newprice":"￥255",
                "oldprice":"￥298"
            },{
                "img": "../img/index/5f8e47b3.jpg",
                "title": "春雨蜂蜜面膜 25g*5片",
                "type":"99元任选2件",
                "newprice":"￥99",
                "oldprice":""
            },{
                "img": "../img/index/3ed0cef9.jpg",
                "title": "城野医生毛孔细致化妆水 100ml",
                "type":"满600送小米手环",
                "newprice":"￥89",
                "oldprice":"￥139"
            }
        ],
        "result2":[
            {
                "img": "https://image.watsons.com.cn//upload/3fc152f0.jpg",
                "imglogo": "https://image.watsons.com.cn//upload/78fa9f95.png",
                "title":"满199减50"
            },{
                "img": "https://image.watsons.com.cn//upload/6c755fd2.jpg",
                "imglogo": "https://image.watsons.com.cn//upload/18648df3.jpg",
                "title":"爆款2折起"
            },{
                "img": "https://image.watsons.com.cn//upload/2f5fb946.jpg",
                "imglogo": "https://image.watsons.com.cn//upload/2de26a1b.jpg",
                "title":"买3免1"
            },{
                "img": "https://image.watsons.com.cn//upload/5477f4c2.jpg",
                "imglogo": "https://image.watsons.com.cn//upload/aef39a2f.jpg",
                "title":"精华买1送1"
            },{
                "img": "https://image.watsons.com.cn//upload/501c0204.png",
                "imglogo": "https://image.watsons.com.cn//upload/96fb96a4.png",
                "title":"爆款面膜19元起"
            },{
                "img": "https://image.watsons.com.cn//upload/4f49002b.jpg",
                "imglogo": "https://image.watsons.com.cn//upload/3ccf8b05.jpg",
                "title":"赢戴森大奖"
            }
        ],
        "result3":{
            "data1":[{
                "Titleimg":"../img/index/con1.jpg",
                "list1":[{
                    "img": "../img/index/1d55d607.jpg",
                    "title": "优理氏烟酰胺亮肤安瓶原液1ml*7支",
                    "type":"买1盒送4盒",
                    "newprice":"￥99",
                    "oldprice":"￥118"
                },{
                    "img": "../img/index/1d55d607.jpg",
                    "title": "优理氏烟酰胺亮肤安瓶原液1ml*7支",
                    "type":"买1盒送4盒",
                    "newprice":"￥99",
                    "oldprice":"￥118"
                },{
                    "img": "../img/index/1d55d607.jpg",
                    "title": "优理氏烟酰胺亮肤安瓶原液1ml*7支",
                    "type":"买1盒送4盒",
                    "newprice":"￥99",
                    "oldprice":"￥118"
                },{
                    "img": "../img/index/1d55d607.jpg",
                    "title": "优理氏烟酰胺亮肤安瓶原液1ml*7支",
                    "type":"买1盒送4盒",
                    "newprice":"￥99",
                    "oldprice":"￥118"
                },{
                    "img": "../img/index/1d55d607.jpg",
                    "title": "优理氏烟酰胺亮肤安瓶原液1ml*7支",
                    "type":"买1盒送4盒",
                    "newprice":"￥99",
                    "oldprice":"￥118"
                },{
                    "img": "../img/index/1d55d607.jpg",
                    "title": "优理氏烟酰胺亮肤安瓶原液1ml*7支",
                    "type":"买1盒送4盒",
                    "newprice":"￥99",
                    "oldprice":"￥118"
                },{
                    "img": "../img/index/1d55d607.jpg",
                    "title": "优理氏烟酰胺亮肤安瓶原液1ml*7支",
                    "type":"买1盒送4盒",
                    "newprice":"￥99",
                    "oldprice":"￥118"
                },{
                    "img": "../img/index/1d55d607.jpg",
                    "title": "优理氏烟酰胺亮肤安瓶原液1ml*7支",
                    "type":"买1盒送4盒",
                    "newprice":"￥99",
                    "oldprice":"￥118"
                },{
                    "img": "../img/index/1d55d607.jpg",
                    "title": "优理氏烟酰胺亮肤安瓶原液1ml*7支",
                    "type":"买1盒送4盒",
                    "newprice":"￥99",
                    "oldprice":"￥118"
                },{
                    "img": "../img/index/1d55d607.jpg",
                    "title": "优理氏烟酰胺亮肤安瓶原液1ml*7支",
                    "type":"买1盒送4盒",
                    "newprice":"￥99",
                    "oldprice":"￥118"
                }]
            }],
            "data2":[{
                "Titleimg":"https://image.watsons.com.cn//upload/ff13f298.jpg?x-oss-process=image/quality,q_80/format,webp",
                "list1":[{
                    "img": "https://image.watsons.com.cn//upload/1d55d607.jpg?x-oss-process=image/resize,w_375/quality,q_80/format,webp",
                    "title": "优理氏烟酰胺亮肤安瓶原液1ml*7支",
                    "type":"买1盒送4盒",
                    "newprice":"￥919",
                    "oldprice":"￥118"
                },{
                    "img": "https://image.watsons.com.cn//upload/1d55d607.jpg?x-oss-process=image/resize,w_375/quality,q_80/format,webp",
                    "title": "优理氏烟酰胺亮肤安瓶原液1ml*7支",
                    "type":"买1盒送4盒",
                    "newprice":"￥99",
                    "oldprice":"￥118"
                },{
                    "img": "https://image.watsons.com.cn//upload/1d55d607.jpg?x-oss-process=image/resize,w_375/quality,q_80/format,webp",
                    "title": "优理氏烟酰胺亮肤安瓶原液1ml*7支",
                    "type":"买1盒送4盒",
                    "newprice":"￥99",
                    "oldprice":"￥118"
                },{
                    "img": "https://image.watsons.com.cn//upload/1d55d607.jpg?x-oss-process=image/resize,w_375/quality,q_80/format,webp",
                    "title": "优理氏烟酰胺亮肤安瓶原液1ml*7支",
                    "type":"买1盒送4盒",
                    "newprice":"￥99",
                    "oldprice":"￥118"
                },{
                    "img": "https://image.watsons.com.cn//upload/1d55d607.jpg?x-oss-process=image/resize,w_375/quality,q_80/format,webp",
                    "title": "优理氏烟酰胺亮肤安瓶原液1ml*7支",
                    "type":"买1盒送4盒",
                    "newprice":"￥99",
                    "oldprice":"￥118"
                },{
                    "img": "https://image.watsons.com.cn//upload/1d55d607.jpg?x-oss-process=image/resize,w_375/quality,q_80/format,webp",
                    "title": "优理氏烟酰胺亮肤安瓶原液1ml*7支",
                    "type":"买1盒送4盒",
                    "newprice":"￥99",
                    "oldprice":"￥118"
                },{
                    "img": "https://image.watsons.com.cn//upload/1d55d607.jpg?x-oss-process=image/resize,w_375/quality,q_80/format,webp",
                    "title": "优理氏烟酰胺亮肤安瓶原液1ml*7支",
                    "type":"买1盒送4盒",
                    "newprice":"￥99",
                    "oldprice":"￥118"
                },{
                    "img": "https://image.watsons.com.cn//upload/1d55d607.jpg?x-oss-process=image/resize,w_375/quality,q_80/format,webp",
                    "title": "优理氏烟酰胺亮肤安瓶原液1ml*7支",
                    "type":"买1盒送4盒",
                    "newprice":"￥99",
                    "oldprice":"￥118"
                },{
                    "img": "https://image.watsons.com.cn//upload/1d55d607.jpg?x-oss-process=image/resize,w_375/quality,q_80/format,webp",
                    "title": "优理氏烟酰胺亮肤安瓶原液1ml*7支",
                    "type":"买1盒送4盒",
                    "newprice":"￥99",
                    "oldprice":"￥118"
                },{
                    "img": "https://image.watsons.com.cn//upload/1d55d607.jpg?x-oss-process=image/resize,w_375/quality,q_80/format,webp",
                    "title": "优理氏烟酰胺亮肤安瓶原液1ml*7支",
                    "type":"买1盒送4盒",
                    "newprice":"￥99",
                    "oldprice":"￥118"
                }]
            }],
            "data3":[{
                "Titleimg":"https://image.watsons.com.cn//upload/ff13f298.jpg?x-oss-process=image/quality,q_80/format,webp",
                "list1":[{
                    "img": "https://image.watsons.com.cn//upload/1d55d607.jpg?x-oss-process=image/resize,w_375/quality,q_80/format,webp",
                    "title": "优理氏烟酰胺亮肤安瓶原液1ml*7支",
                    "type":"买1盒送4盒",
                    "newprice":"￥99",
                    "oldprice":"￥118"
                },{
                    "img": "https://image.watsons.com.cn//upload/1d55d607.jpg?x-oss-process=image/resize,w_375/quality,q_80/format,webp",
                    "title": "优理氏烟酰胺亮肤安瓶原液1ml*7支",
                    "type":"买1盒送4盒",
                    "newprice":"￥99",
                    "oldprice":"￥118"
                },{
                    "img": "https://image.watsons.com.cn//upload/1d55d607.jpg?x-oss-process=image/resize,w_375/quality,q_80/format,webp",
                    "title": "优理氏烟酰胺亮肤安瓶原液1ml*7支",
                    "type":"买1盒送4盒",
                    "newprice":"￥99",
                    "oldprice":"￥118"
                },{
                    "img": "https://image.watsons.com.cn//upload/1d55d607.jpg?x-oss-process=image/resize,w_375/quality,q_80/format,webp",
                    "title": "优理氏烟酰胺亮肤安瓶原液1ml*7支",
                    "type":"买1盒送4盒",
                    "newprice":"￥99",
                    "oldprice":"￥118"
                },{
                    "img": "https://image.watsons.com.cn//upload/1d55d607.jpg?x-oss-process=image/resize,w_375/quality,q_80/format,webp",
                    "title": "优理氏烟酰胺亮肤安瓶原液1ml*7支",
                    "type":"买1盒送4盒",
                    "newprice":"￥99",
                    "oldprice":"￥118"
                },{
                    "img": "https://image.watsons.com.cn//upload/1d55d607.jpg?x-oss-process=image/resize,w_375/quality,q_80/format,webp",
                    "title": "优理氏烟酰胺亮肤安瓶原液1ml*7支",
                    "type":"买1盒送4盒",
                    "newprice":"￥99",
                    "oldprice":"￥118"
                },{
                    "img": "https://image.watsons.com.cn//upload/1d55d607.jpg?x-oss-process=image/resize,w_375/quality,q_80/format,webp",
                    "title": "优理氏烟酰胺亮肤安瓶原液1ml*7支",
                    "type":"买1盒送4盒",
                    "newprice":"￥99",
                    "oldprice":"￥118"
                },{
                    "img": "https://image.watsons.com.cn//upload/1d55d607.jpg?x-oss-process=image/resize,w_375/quality,q_80/format,webp",
                    "title": "优理氏烟酰胺亮肤安瓶原液1ml*7支",
                    "type":"买1盒送4盒",
                    "newprice":"￥99",
                    "oldprice":"￥118"
                },{
                    "img": "https://image.watsons.com.cn//upload/1d55d607.jpg?x-oss-process=image/resize,w_375/quality,q_80/format,webp",
                    "title": "优理氏烟酰胺亮肤安瓶原液1ml*7支",
                    "type":"买1盒送4盒",
                    "newprice":"￥99",
                    "oldprice":"￥118"
                },{
                    "img": "https://image.watsons.com.cn//upload/1d55d607.jpg?x-oss-process=image/resize,w_375/quality,q_80/format,webp",
                    "title": "优理氏烟酰胺亮肤安瓶原液1ml*7支",
                    "type":"买1盒送4盒",
                    "newprice":"￥99",
                    "oldprice":"￥118"
                }]
            }],
            "data4":[{
                "Titleimg":"https://image.watsons.com.cn//upload/ff13f298.jpg?x-oss-process=image/quality,q_80/format,webp",
                "list1":[{
                    "img": "https://image.watsons.com.cn//upload/1d55d607.jpg?x-oss-process=image/resize,w_375/quality,q_80/format,webp",
                    "title": "优理氏烟酰胺亮肤安瓶原液1ml*7支",
                    "type":"买1盒送4盒",
                    "newprice":"￥99",
                    "oldprice":"￥118"
                },{
                    "img": "https://image.watsons.com.cn//upload/1d55d607.jpg?x-oss-process=image/resize,w_375/quality,q_80/format,webp",
                    "title": "优理氏烟酰胺亮肤安瓶原液1ml*7支",
                    "type":"买1盒送4盒",
                    "newprice":"￥99",
                    "oldprice":"￥118"
                },{
                    "img": "https://image.watsons.com.cn//upload/1d55d607.jpg?x-oss-process=image/resize,w_375/quality,q_80/format,webp",
                    "title": "优理氏烟酰胺亮肤安瓶原液1ml*7支",
                    "type":"买1盒送4盒",
                    "newprice":"￥99",
                    "oldprice":"￥118"
                },{
                    "img": "https://image.watsons.com.cn//upload/1d55d607.jpg?x-oss-process=image/resize,w_375/quality,q_80/format,webp",
                    "title": "优理氏烟酰胺亮肤安瓶原液1ml*7支",
                    "type":"买1盒送4盒",
                    "newprice":"￥99",
                    "oldprice":"￥118"
                },{
                    "img": "https://image.watsons.com.cn//upload/1d55d607.jpg?x-oss-process=image/resize,w_375/quality,q_80/format,webp",
                    "title": "优理氏烟酰胺亮肤安瓶原液1ml*7支",
                    "type":"买1盒送4盒",
                    "newprice":"￥99",
                    "oldprice":"￥118"
                },{
                    "img": "https://image.watsons.com.cn//upload/1d55d607.jpg?x-oss-process=image/resize,w_375/quality,q_80/format,webp",
                    "title": "优理氏烟酰胺亮肤安瓶原液1ml*7支",
                    "type":"买1盒送4盒",
                    "newprice":"￥99",
                    "oldprice":"￥118"
                },{
                    "img": "https://image.watsons.com.cn//upload/1d55d607.jpg?x-oss-process=image/resize,w_375/quality,q_80/format,webp",
                    "title": "优理氏烟酰胺亮肤安瓶原液1ml*7支",
                    "type":"买1盒送4盒",
                    "newprice":"￥99",
                    "oldprice":"￥118"
                },{
                    "img": "https://image.watsons.com.cn//upload/1d55d607.jpg?x-oss-process=image/resize,w_375/quality,q_80/format,webp",
                    "title": "优理氏烟酰胺亮肤安瓶原液1ml*7支",
                    "type":"买1盒送4盒",
                    "newprice":"￥99",
                    "oldprice":"￥118"
                },{
                    "img": "https://image.watsons.com.cn//upload/1d55d607.jpg?x-oss-process=image/resize,w_375/quality,q_80/format,webp",
                    "title": "优理氏烟酰胺亮肤安瓶原液1ml*7支",
                    "type":"买1盒送4盒",
                    "newprice":"￥99",
                    "oldprice":"￥118"
                },{
                    "img": "https://image.watsons.com.cn//upload/1d55d607.jpg?x-oss-process=image/resize,w_375/quality,q_80/format,webp",
                    "title": "优理氏烟酰胺亮肤安瓶原液1ml*7支",
                    "type":"买1盒送4盒",
                    "newprice":"￥99",
                    "oldprice":"￥118"
                }]
            }],
            "data5":[{
                "Titleimg":"https://image.watsons.com.cn//upload/ff13f298.jpg?x-oss-process=image/quality,q_80/format,webp",
                "list1":[{
                    "img": "https://image.watsons.com.cn//upload/1d55d607.jpg?x-oss-process=image/resize,w_375/quality,q_80/format,webp",
                    "title": "优理氏烟酰胺亮肤安瓶原液1ml*7支",
                    "type":"买1盒送4盒",
                    "newprice":"￥99",
                    "oldprice":"￥118"
                },{
                    "img": "https://image.watsons.com.cn//upload/1d55d607.jpg?x-oss-process=image/resize,w_375/quality,q_80/format,webp",
                    "title": "优理氏烟酰胺亮肤安瓶原液1ml*7支",
                    "type":"买1盒送4盒",
                    "newprice":"￥99",
                    "oldprice":"￥118"
                },{
                    "img": "https://image.watsons.com.cn//upload/1d55d607.jpg?x-oss-process=image/resize,w_375/quality,q_80/format,webp",
                    "title": "优理氏烟酰胺亮肤安瓶原液1ml*7支",
                    "type":"买1盒送4盒",
                    "newprice":"￥99",
                    "oldprice":"￥118"
                },{
                    "img": "https://image.watsons.com.cn//upload/1d55d607.jpg?x-oss-process=image/resize,w_375/quality,q_80/format,webp",
                    "title": "优理氏烟酰胺亮肤安瓶原液1ml*7支",
                    "type":"买1盒送4盒",
                    "newprice":"￥99",
                    "oldprice":"￥118"
                },{
                    "img": "https://image.watsons.com.cn//upload/1d55d607.jpg?x-oss-process=image/resize,w_375/quality,q_80/format,webp",
                    "title": "优理氏烟酰胺亮肤安瓶原液1ml*7支",
                    "type":"买1盒送4盒",
                    "newprice":"￥99",
                    "oldprice":"￥118"
                },{
                    "img": "https://image.watsons.com.cn//upload/1d55d607.jpg?x-oss-process=image/resize,w_375/quality,q_80/format,webp",
                    "title": "优理氏烟酰胺亮肤安瓶原液1ml*7支",
                    "type":"买1盒送4盒",
                    "newprice":"￥99",
                    "oldprice":"￥118"
                },{
                    "img": "https://image.watsons.com.cn//upload/1d55d607.jpg?x-oss-process=image/resize,w_375/quality,q_80/format,webp",
                    "title": "优理氏烟酰胺亮肤安瓶原液1ml*7支",
                    "type":"买1盒送4盒",
                    "newprice":"￥99",
                    "oldprice":"￥118"
                },{
                    "img": "https://image.watsons.com.cn//upload/1d55d607.jpg?x-oss-process=image/resize,w_375/quality,q_80/format,webp",
                    "title": "优理氏烟酰胺亮肤安瓶原液1ml*7支",
                    "type":"买1盒送4盒",
                    "newprice":"￥99",
                    "oldprice":"￥118"
                },{
                    "img": "https://image.watsons.com.cn//upload/1d55d607.jpg?x-oss-process=image/resize,w_375/quality,q_80/format,webp",
                    "title": "优理氏烟酰胺亮肤安瓶原液1ml*7支",
                    "type":"买1盒送4盒",
                    "newprice":"￥99",
                    "oldprice":"￥118"
                },{
                    "img": "https://image.watsons.com.cn//upload/1d55d607.jpg?x-oss-process=image/resize,w_375/quality,q_80/format,webp",
                    "title": "优理氏烟酰胺亮肤安瓶原液1ml*7支",
                    "type":"买1盒送4盒",
                    "newprice":"￥99",
                    "oldprice":"￥118"
                }]
            }],
            "data6":[{
                "Titleimg":"https://image.watsons.com.cn//upload/ff13f298.jpg?x-oss-process=image/quality,q_80/format,webp",
                "list1":[{
                    "img": "https://image.watsons.com.cn//upload/1d55d607.jpg?x-oss-process=image/resize,w_375/quality,q_80/format,webp",
                    "title": "优理氏烟酰胺亮肤安瓶原液1ml*7支",
                    "type":"买1盒送4盒",
                    "newprice":"￥99",
                    "oldprice":"￥118"
                },{
                    "img": "https://image.watsons.com.cn//upload/1d55d607.jpg?x-oss-process=image/resize,w_375/quality,q_80/format,webp",
                    "title": "优理氏烟酰胺亮肤安瓶原液1ml*7支",
                    "type":"买1盒送4盒",
                    "newprice":"￥99",
                    "oldprice":"￥118"
                },{
                    "img": "https://image.watsons.com.cn//upload/1d55d607.jpg?x-oss-process=image/resize,w_375/quality,q_80/format,webp",
                    "title": "优理氏烟酰胺亮肤安瓶原液1ml*7支",
                    "type":"买1盒送4盒",
                    "newprice":"￥99",
                    "oldprice":"￥118"
                },{
                    "img": "https://image.watsons.com.cn//upload/1d55d607.jpg?x-oss-process=image/resize,w_375/quality,q_80/format,webp",
                    "title": "优理氏烟酰胺亮肤安瓶原液1ml*7支",
                    "type":"买1盒送4盒",
                    "newprice":"￥99",
                    "oldprice":"￥118"
                },{
                    "img": "https://image.watsons.com.cn//upload/1d55d607.jpg?x-oss-process=image/resize,w_375/quality,q_80/format,webp",
                    "title": "优理氏烟酰胺亮肤安瓶原液1ml*7支",
                    "type":"买1盒送4盒",
                    "newprice":"￥99",
                    "oldprice":"￥118"
                },{
                    "img": "https://image.watsons.com.cn//upload/1d55d607.jpg?x-oss-process=image/resize,w_375/quality,q_80/format,webp",
                    "title": "优理氏烟酰胺亮肤安瓶原液1ml*7支",
                    "type":"买1盒送4盒",
                    "newprice":"￥99",
                    "oldprice":"￥118"
                },{
                    "img": "https://image.watsons.com.cn//upload/1d55d607.jpg?x-oss-process=image/resize,w_375/quality,q_80/format,webp",
                    "title": "优理氏烟酰胺亮肤安瓶原液1ml*7支",
                    "type":"买1盒送4盒",
                    "newprice":"￥99",
                    "oldprice":"￥118"
                },{
                    "img": "https://image.watsons.com.cn//upload/1d55d607.jpg?x-oss-process=image/resize,w_375/quality,q_80/format,webp",
                    "title": "优理氏烟酰胺亮肤安瓶原液1ml*7支",
                    "type":"买1盒送4盒",
                    "newprice":"￥99",
                    "oldprice":"￥118"
                },{
                    "img": "https://image.watsons.com.cn//upload/1d55d607.jpg?x-oss-process=image/resize,w_375/quality,q_80/format,webp",
                    "title": "优理氏烟酰胺亮肤安瓶原液1ml*7支",
                    "type":"买1盒送4盒",
                    "newprice":"￥99",
                    "oldprice":"￥118"
                },{
                    "img": "https://image.watsons.com.cn//upload/1d55d607.jpg?x-oss-process=image/resize,w_375/quality,q_80/format,webp",
                    "title": "优理氏烟酰胺亮肤安瓶原液1ml*7支",
                    "type":"买1盒送4盒",
                    "newprice":"￥99",
                    "oldprice":"￥118"
                }]
            }]},
        "result4":[
            {
                "img": "https://image.watsons.com.cn//upload/9dbfad30.jpg?x-oss-process=image/quality,q_80/format,webp"
            },{
                "img": "https://image.watsons.com.cn//upload/25488f70.jpg?x-oss-process=image/quality,q_80/format,webp"
            },{
                "img": "https://image.watsons.com.cn//upload/2f52ea5f.jpg?x-oss-process=image/quality,q_80/format,webp"
            },{
                "img": "https://image.watsons.com.cn//upload/25412d80.jpg?x-oss-process=image/quality,q_80/format,webp"
            },{
                "img": "https://image.watsons.com.cn//upload/b0c7ab1d.jpg?x-oss-process=image/quality,q_80/format,webp"
            },{
                "img": "https://image.watsons.com.cn//upload/1ecd149a.jpg?x-oss-process=image/quality,q_80/format,webp"
            },{
                "img": "https://image.watsons.com.cn//upload/88fd1137.jpg?x-oss-process=image/quality,q_80/format,webp"
            },{
                "img": "https://image.watsons.com.cn//upload/a9f40414.jpg?x-oss-process=image/quality,q_80/format,webp"
            },{
                "img": "https://image.watsons.com.cn//upload/54e2f618.jpg?x-oss-process=image/quality,q_80/format,webp"
            },{
                "img": "https://image.watsons.com.cn//upload/20ab80d9.jpg?x-oss-process=image/quality,q_80/format,webp"
            },{
                "img": "https://image.watsons.com.cn//upload/634d7774.jpg?x-oss-process=image/quality,q_80/format,webp"
            },{
                "img": "https://image.watsons.com.cn//upload/6659ca04.jpg?x-oss-process=image/quality,q_80/format,webp"
            },{
                "img": "https://image.watsons.com.cn//upload/c673ebe2.jpg?x-oss-process=image/quality,q_80/format,webp"
            },{
                "img": "https://image.watsons.com.cn//upload/a5588893.jpg?x-oss-process=image/quality,q_80/format,webp"
            },{
                "img": "https://image.watsons.com.cn//upload/11d960fd.jpg?x-oss-process=image/quality,q_80/format,webp"
            },{
                "img": "https://image.watsons.com.cn//upload/cddf2e56.jpg?x-oss-process=image/quality,q_80/format,webp"
            },{
                "img": "https://image.watsons.com.cn//upload/e31166e8.jpg?x-oss-process=image/quality,q_80/format,webp"
            },{
                "img": "https://image.watsons.com.cn//upload/c23d9d13.jpg?x-oss-process=image/quality,q_80/format,webp"
            },{
                "img": "https://image.watsons.com.cn//upload/b6da6163.jpg?x-oss-process=image/quality,q_80/format,webp"
            },{
                "img": "https://image.watsons.com.cn//upload/7ca99cdf.jpg?x-oss-process=image/quality,q_80/format,webp"
            },{
                "img": "https://image.watsons.com.cn//upload/8d7c7de5.jpg?x-oss-process=image/quality,q_80/format,webp"
            },{
                "img": "https://image.watsons.com.cn//upload/5c8606e0.jpg?x-oss-process=image/quality,q_80/format,webp"
            },{
                "img": "https://image.watsons.com.cn//upload/3678f0a6.jpg?x-oss-process=image/quality,q_80/format,webp"
            },{
                "img": "https://image.watsons.com.cn//upload/29d3f4e0.jpg?x-oss-process=image/quality,q_80/format,webp"
            },{
                "img": "https://image.watsons.com.cn//upload/1aa018fc.jpg?x-oss-process=image/quality,q_80/format,webp"
            },{
                "img": "https://image.watsons.com.cn//upload/0fd8db02.jpg?x-oss-process=image/quality,q_80/format,webp"
            },{
                "img": "https://image.watsons.com.cn//upload/b66cb468.jpg?x-oss-process=image/quality,q_80/format,webp"
            },{
                "img": "https://image.watsons.com.cn//upload/0f9a0b21.jpg?x-oss-process=image/quality,q_80/format,webp"
            },{
                "img": "https://image.watsons.com.cn//upload/7ebe5e4f.jpg?x-oss-process=image/quality,q_80/format,webp"
            },{
                "img": "https://image.watsons.com.cn//upload/4df6baf7.jpg?x-oss-process=image/quality,q_80/format,webp"
            },{
                "img": "https://image.watsons.com.cn//upload/0217a51f.jpg?x-oss-process=image/quality,q_80/format,webp"
            },{
                "img": "https://image.watsons.com.cn//upload/d904f545.jpg?x-oss-process=image/quality,q_80/format,webp"
            },{
                "img": "https://image.watsons.com.cn//upload/3aeaae47.jpg?x-oss-process=image/quality,q_80/format,webp"
            },{
                "img": "https://image.watsons.com.cn//upload/cf3edbe5.jpg?x-oss-process=image/quality,q_80/format,webp"
            },{
                "img": "https://image.watsons.com.cn//upload/3e81b250.jpg?x-oss-process=image/quality,q_80/format,webp"
            },{
                "img": "https://image.watsons.com.cn//upload/ae44e1c0.png?x-oss-process=image/quality,q_80/format,webp"
            },{
                "img": "https://image.watsons.com.cn//upload/ccabe431.jpeg?x-oss-process=image/quality,q_80/format,webp"
            },{
                "img": "https://image.watsons.com.cn//upload/15460de8.jpg?x-oss-process=image/quality,q_80/format,webp"
            },{
                "img": "https://image.watsons.com.cn//upload/119b0502.jpg?x-oss-process=image/quality,q_80/format,webp"
            },{
                "img": "https://image.watsons.com.cn//upload/89156690.jpg?x-oss-process=image/quality,q_80/format,webp"
            },{
                "img": "https://image.watsons.com.cn//upload/7a19a18b.png?x-oss-process=image/quality,q_80/format,webp"
            },{
                "img": "https://image.watsons.com.cn//upload/8e805962.jpg?x-oss-process=image/quality,q_80/format,webp"
            },{
                "img": "https://image.watsons.com.cn//upload/e2157bd9.jpg?x-oss-process=image/quality,q_80/format,webp"
            },{
                "img": "https://image.watsons.com.cn//upload/ed925be7.jpg?x-oss-process=image/quality,q_80/format,webp"
            },{
                "img": "https://image.watsons.com.cn//upload/d31a2b11.jpg?x-oss-process=image/quality,q_80/format,webp"
            },{
                "img": "https://image.watsons.com.cn//upload/676c9dee.jpg?x-oss-process=image/quality,q_80/format,webp"
            },{
                "img": "https://image.watsons.com.cn//upload/4028be62.jpg?x-oss-process=image/quality,q_80/format,webp"
            },{
                "img": "https://image.watsons.com.cn//upload/1caf62c0.jpg?x-oss-process=image/quality,q_80/format,webp"
            },{
                "img": "https://image.watsons.com.cn//upload/071ebf25.jpg?x-oss-process=image/quality,q_80/format,webp"
            },{
                "img": "https://image.watsons.com.cn//upload/2d369b0a.jpg?x-oss-process=image/quality,q_80/format,webp"
            },{
                "img": "https://image.watsons.com.cn//upload/694d2104.jpg?x-oss-process=image/quality,q_80/format,webp"
            },{
                "img": "https://image.watsons.com.cn//upload/e65f7cbc.jpg?x-oss-process=image/quality,q_80/format,webp"
            },{
                "img": "https://image.watsons.com.cn//upload/cefb6663.jpg?x-oss-process=image/quality,q_80/format,webp"
            },{
                "img": "https://image.watsons.com.cn//upload/bf438339.jpg?x-oss-process=image/quality,q_80/format,webp"
            },{
                "img": "https://image.watsons.com.cn//upload/a0716610.jpg?x-oss-process=image/quality,q_80/format,webp"
            },{
                "img": "https://image.watsons.com.cn//upload/79b947ce.jpg?x-oss-process=image/quality,q_80/format,webp"
            },{
                "img": "https://image.watsons.com.cn//upload/eef4eb2a.jpg?x-oss-process=image/quality,q_80/format,webp"
            },{
                "img": "https://image.watsons.com.cn//upload/9486e74d.jpg?x-oss-process=image/quality,q_80/format,webp"
            },{
                "img": "https://image.watsons.com.cn//upload/c74c9b82.jpg?x-oss-process=image/quality,q_80/format,webp"
            },{
                "img": "https://image.watsons.com.cn//upload/a6e362a7.jpg?x-oss-process=image/quality,q_80/format,webp"
            },{
                "img": "https://image.watsons.com.cn//upload/577ea5b5.jpg?x-oss-process=image/quality,q_80/format,webp"
            },{
                "img": "https://image.watsons.com.cn//upload/3b06a7e0.jpg?x-oss-process=image/quality,q_80/format,webp"
            },{
                "img": "https://image.watsons.com.cn//upload/097dbf07.jpg?x-oss-process=image/quality,q_80/format,webp"
            },{
                "img": "https://image.watsons.com.cn//upload/2cd912fc.jpg?x-oss-process=image/quality,q_80/format,webp"
            },{
                "img": "https://image.watsons.com.cn//upload/ecd2fb9f.jpg?x-oss-process=image/quality,q_80/format,webp"
            },{
                "img": "https://image.watsons.com.cn//upload/7ce36f43.jpg?x-oss-process=image/quality,q_80/format,webp"
            },{
                "img": "https://image.watsons.com.cn//upload/48ed686d.jpg?x-oss-process=image/quality,q_80/format,webp"
            },{
                "img": "https://image.watsons.com.cn//upload/2e3126be.jpg?x-oss-process=image/quality,q_80/format,webp"
            },{
                "img": "https://image.watsons.com.cn//upload/06c90597.jpg?x-oss-process=image/quality,q_80/format,webp"
            },{
                "img": "https://image.watsons.com.cn//upload/934eea01.jpg?x-oss-process=image/quality,q_80/format,webp"
            },{
                "img": "https://image.watsons.com.cn//upload/f73739c5.jpg?x-oss-process=image/quality,q_80/format,webp"
            },{
                "img": "https://image.watsons.com.cn//upload/fe917ffd.jpg?x-oss-process=image/quality,q_80/format,webp"
            },{
                "img": "https://image.watsons.com.cn//upload/8c28b5e6.jpg?x-oss-process=image/quality,q_80/format,webp"
            },{
                "img": "https://image.watsons.com.cn//upload/e2899fc6.jpg?x-oss-process=image/quality,q_80/format,webp"
            },{
                "img": "https://image.watsons.com.cn//upload/616e90f1.jpg?x-oss-process=image/quality,q_80/format,webp"
            },{
                "img": "https://image.watsons.com.cn//upload/5a3bed9f.jpg?x-oss-process=image/quality,q_80/format,webp"
            },{
                "img": "https://image.watsons.com.cn//upload/662b5b65.jpg?x-oss-process=image/quality,q_80/format,webp"
            }
        ]
    }
  }